funimage/__init__.py
funimage/convert.py
funimage/capture/__init__.py
funimage/capture/_queue.py
funimage-1.0.19.dist-info/METADATA
funimage-1.0.19.dist-info/WHEEL
funimage-1.0.19.dist-info/top_level.txt
funimage-1.0.19.dist-info/RECORD
