Metadata-Version: 2.4
Name: funimage
Version: 1.0.19
Summary: A powerful Python library for image format conversion and processing
Author-email: 牛哥 <niuliangtao@qq.com>, farfarfun <farfarfun@qq.com>
Maintainer-email: 牛哥 <niuliangtao@qq.com>, farfarfun <farfarfun@qq.com>
License: MIT
Project-URL: Organization, https://github.com/farfarfun
Project-URL: Repository, https://github.com/farfarfun/funimage
Project-URL: Releases, https://github.com/farfarfun/funimage/releases
Keywords: image,conversion,PIL,opencv,base64,processing
Classifier: Development Status :: 5 - Production/Stable
Classifier: Intended Audience :: Developers
Classifier: License :: OSI Approved :: MIT License
Classifier: Programming Language :: Python :: 3
Classifier: Programming Language :: Python :: 3.8
Classifier: Programming Language :: Python :: 3.9
Classifier: Programming Language :: Python :: 3.10
Classifier: Programming Language :: Python :: 3.11
Classifier: Programming Language :: Python :: 3.12
Classifier: Topic :: Software Development :: Libraries :: Python Modules
Classifier: Topic :: Multimedia :: Graphics
Requires-Python: >=3.8
Requires-Dist: funfake>=1.0.3
Requires-Dist: funutil>=1.0.14
Requires-Dist: pillow>=9.0.0
Requires-Dist: pillow-avif-plugin>=1.4.6
Requires-Dist: numpy>=1.20.0
Provides-Extra: opencv
Requires-Dist: opencv-python>=4.5.0; extra == "opencv"
